kamae/__init__.py
kamae/graph/__init__.py
kamae/graph/pipeline_graph.py
kamae/sklearn/__init__.py
kamae/sklearn/estimators/__init__.py
kamae/sklearn/estimators/standard_scale.py
kamae/sklearn/params/__init__.py
kamae/sklearn/params/base.py
kamae/sklearn/params/name.py
kamae/sklearn/params/utils.py
kamae/sklearn/pipeline/__init__.py
kamae/sklearn/pipeline/pipeline.py
kamae/sklearn/transformers/__init__.py
kamae/sklearn/transformers/array_concatenate.py
kamae/sklearn/transformers/array_split.py
kamae/sklearn/transformers/base.py
kamae/sklearn/transformers/identity.py
kamae/sklearn/transformers/log.py
kamae/spark/__init__.py
kamae/spark/common/__init__.py
kamae/spark/common/spark_operation.py
kamae/spark/estimators/__init__.py
kamae/spark/estimators/base.py
kamae/spark/estimators/conditional_standard_scale.py
kamae/spark/estimators/impute.py
kamae/spark/estimators/min_max_scale.py
kamae/spark/estimators/one_hot_encode.py
kamae/spark/estimators/shared_one_hot_encode.py
kamae/spark/estimators/shared_string_index.py
kamae/spark/estimators/single_feature_array_standard_scale.py
kamae/spark/estimators/standard_scale.py
kamae/spark/estimators/string_index.py
kamae/spark/params/__init__.py
kamae/spark/params/base.py
kamae/spark/params/default_read_write.py
kamae/spark/params/name.py
kamae/spark/params/shared.py
kamae/spark/params/utils.py
kamae/spark/pipeline/__init__.py
kamae/spark/pipeline/pipeline.py
kamae/spark/pipeline/pipeline_model.py
kamae/spark/transformers/__init__.py
kamae/spark/transformers/absolute_value.py
kamae/spark/transformers/array_concatenate.py
kamae/spark/transformers/array_crop.py
kamae/spark/transformers/array_split.py
kamae/spark/transformers/array_subtract_minimum.py
kamae/spark/transformers/base.py
kamae/spark/transformers/bearing_angle.py
kamae/spark/transformers/bin.py
kamae/spark/transformers/bloom_encode.py
kamae/spark/transformers/bucketize.py
kamae/spark/transformers/conditional_standard_scale.py
kamae/spark/transformers/cosine_similarity.py
kamae-2.38.1.dist-info/licenses/LICENSE.txt
kamae-2.38.1.dist-info/METADATA
kamae-2.38.1.dist-info/WHEEL
kamae-2.38.1.dist-info/top_level.txt
kamae-2.38.1.dist-info/RECORD
