Metadata-Version: 2.4
Name: kamae
Version: 2.38.1
Summary: Feature engineering for big data and quick inference.
Author-email: Expedia Group <oss@expediagroup.com>
License-Expression: Apache-2.0
Requires-Python: <3.13,>=3.8.1
License-File: LICENSE.txt
Requires-Dist: pyspark<4.0.0,>=3.4.0
Requires-Dist: pandas<2.0.0,>=1.3.4
Requires-Dist: networkx<3.0.0,>=2.6.3
Requires-Dist: pyfarmhash<0.4.0,>=0.3.2
Requires-Dist: keras-tuner<2.0.0,>=1.0.4
Requires-Dist: scikit-learn<2.0.0,>=1.0.0
Requires-Dist: joblib<2.0.0,>=1.0.0
Requires-Dist: numpy<2.0.0,>=1.22.0
Requires-Dist: tensorflow<2.19.0,>=2.9.1
Requires-Dist: dill<1.0.0,>=0.3.0
Dynamic: license-file
